chexmate/__init__.py
chexmate/seamless_chex.py
chexmate/test_bank_accounts.py
chexmate/endpoints/__init__.py
chexmate/endpoints/base_endpoint.py
chexmate/endpoints/create_a_check_endpoint.py
chexmate/endpoints/endpoints.py
chexmate/endpoints/request_parameters/__init__.py
chexmate/endpoints/request_parameters/parameter_requirement.py
chexmate/endpoints/request_parameters/parameter_restriction.py
chexmate/endpoints/request_parameters/request_parameter.py
chexmate/endpoints/request_parameters/request_parameter_list.py
chexmate/enums/__init__.py
chexmate/enums/content_type_enum.py
chexmate/enums/fund_confirmation_enum.py
chexmate/enums/http_method_enum.py
chexmate/enums/risk_enum.py
chexmate/enums/routing_number_enum.py
chexmate/enums/seamless_chex_base_url_enum.py
chexmate-0.0.8.dist-info/LICENSE
chexmate-0.0.8.dist-info/METADATA
chexmate-0.0.8.dist-info/WHEEL
chexmate-0.0.8.dist-info/top_level.txt
chexmate-0.0.8.dist-info/RECORD
