Metadata-Version: 2.1
Name: chexmate
Version: 0.0.8
Summary: An (unofficial and incomplete) package used to integrate with the SeamlessChex API quickly and easily.
Home-page: https://github.com/Faugermire/chexmate
Author: William Hinz
Author-email: faugermire@gmail.com
Classifier: Programming Language :: Python :: 3
Classifier: License :: OSI Approved :: MIT License
Classifier: Operating System :: OS Independent
Requires-Python: >=3.12
License-File: LICENSE
Requires-Dist: setuptools~=75.6.0
Requires-Dist: requests~=2.32.3
